odoo/addons/sell_only_by_packaging/README.rst
odoo/addons/sell_only_by_packaging/__init__.py
odoo/addons/sell_only_by_packaging/__manifest__.py
odoo/addons/sell_only_by_packaging/i18n/es.po
odoo/addons/sell_only_by_packaging/i18n/it.po
odoo/addons/sell_only_by_packaging/i18n/sell_only_by_packaging.pot
odoo/addons/sell_only_by_packaging/models/__init__.py
odoo/addons/sell_only_by_packaging/models/product_packaging.py
odoo/addons/sell_only_by_packaging/models/product_packaging_level.py
odoo/addons/sell_only_by_packaging/models/product_product.py
odoo/addons/sell_only_by_packaging/models/product_template.py
odoo/addons/sell_only_by_packaging/models/sale_order_line.py
odoo/addons/sell_only_by_packaging/readme/CONFIGURE.md
odoo/addons/sell_only_by_packaging/readme/CONTRIBUTORS.md
odoo/addons/sell_only_by_packaging/readme/CREDITS.md
odoo/addons/sell_only_by_packaging/readme/DESCRIPTION.md
odoo/addons/sell_only_by_packaging/static/description/icon.png
odoo/addons/sell_only_by_packaging/static/description/index.html
odoo/addons/sell_only_by_packaging/tests/__init__.py
odoo/addons/sell_only_by_packaging/tests/common.py
odoo/addons/sell_only_by_packaging/tests/test_minimum_sellable_qty.py
odoo/addons/sell_only_by_packaging/tests/test_sale_line_onchanges.py
odoo/addons/sell_only_by_packaging/tests/test_sale_only_by_packaging.py
odoo/addons/sell_only_by_packaging/views/product_packaging.xml
odoo/addons/sell_only_by_packaging/views/product_product.xml
odoo/addons/sell_only_by_packaging/views/product_template.xml
odoo_addon_sell_only_by_packaging-18.0.1.1.0.dist-info/METADATA
odoo_addon_sell_only_by_packaging-18.0.1.1.0.dist-info/WHEEL
odoo_addon_sell_only_by_packaging-18.0.1.1.0.dist-info/top_level.txt
odoo_addon_sell_only_by_packaging-18.0.1.1.0.dist-info/RECORD
