Metadata-Version: 2.1
Name: odoo-addon-sell_only_by_packaging
Version: 18.0.1.1.0
Requires-Python: >=3.10
Requires-Dist: odoo-addon-product_packaging_level_salable==18.0.*
Requires-Dist: odoo==18.0.*
Summary: Manage sale of packaging
Home-page: https://github.com/OCA/sale-workflow
License: AGPL-3
Author: Camptocamp, BCIM, Odoo Community Association (OCA)
Author-email: support@odoo-community.org
Classifier: Programming Language :: Python
Classifier: Framework :: Odoo
Classifier: Framework :: Odoo :: 18.0
Classifier: License :: OSI Approved :: GNU Affero General Public License v3
Classifier: Development Status :: 3 - Alpha
